LICENSE
MANIFEST.in
README.rst
setup.cfg
setup.py
sms_log_handler/__init__.py
sms_log_handler/sms_handler.py
sms_log_handler/utils.py
sms_log_handler.egg-info/PKG-INFO
sms_log_handler.egg-info/SOURCES.txt
sms_log_handler.egg-info/dependency_links.txt
sms_log_handler.egg-info/requires.txt
sms_log_handler.egg-info/top_level.txt
sms_log_handler/providers/__init__.py
sms_log_handler/providers/africastalking.py
sms_log_handler/providers/base.py